DEVELOPING.rst
LICENSE.txt
LICENSE_COLORBREWER.txt
LICENSE_YORICK.txt
MANIFEST.in
README-tvtk.txt
README.rst
image_LICENSE.txt
image_LICENSE_CP.txt
image_LICENSE_Eclipse.txt
image_LICENSE_Nuvola.txt
image_LICENSE_OOo.txt
mlab_reference.py
pyproject.toml
setup.cfg
setup.py
artwork/mayavi-banner.jpg
artwork/dataset_diagram/dataset_diagram.svg
artwork/dataset_diagram/structured_points.jpg
artwork/dataset_diagram/structured_points_connected.jpg
artwork/dataset_diagram/unstructured_points.jpg
artwork/dataset_diagram/unstructured_points_cell_data.jpg
artwork/dataset_diagram/unstructured_points_connected.jpg
artwork/dataset_diagram/unstructured_points_scalar_data.jpg
artwork/dataset_diagram/unstructured_points_scalar_data_labels.jpg
artwork/dataset_diagram/unstructured_points_vector_data.jpg
docs/API.txt
docs/CHANGES.txt
docs/DEVELOPMENT.txt
docs/Makefile
docs/MakefileMayavi
docs/MakefileTVTK
docs/THANKS.txt
docs/TODO.txt
docs/mayavi2.man
docs/source/render_examples.py
docs/source/render_images.py
docs/source/mayavi/advanced_scripting.rst
docs/source/mayavi/advanced_use.rst
docs/source/mayavi/application.rst
docs/source/mayavi/bugs.rst
docs/source/mayavi/building_applications.rst
docs/source/mayavi/changes.rst
docs/source/mayavi/citation.bib
docs/source/mayavi/clamping_off.jpg
docs/source/mayavi/clamping_on.jpg
docs/source/mayavi/conf.py
docs/source/mayavi/data.rst
docs/source/mayavi/example_exploring_a_vector_field.rst
docs/source/mayavi/example_fire.rst
docs/source/mayavi/example_gradient.jpg
docs/source/mayavi/example_heart.rst
docs/source/mayavi/example_parametric_surface.rst
docs/source/mayavi/example_potential.jpg
docs/source/mayavi/example_potential_ipython.jpg
docs/source/mayavi/example_streamline.jpg
docs/source/mayavi/example_trajectories.jpg
docs/source/mayavi/example_using_with_scipy.rst
docs/source/mayavi/example_vector_cut_plane.jpg
docs/source/mayavi/examples.rst
docs/source/mayavi/filters.rst
docs/source/mayavi/image_data.jpg
docs/source/mayavi/index.rst
mayavi.egg-info/PKG-INFO
mayavi.egg-info/SOURCES.txt
mayavi.egg-info/dependency_links.txt
mayavi.egg-info/entry_points.txt
mayavi.egg-info/not-zip-safe
mayavi.egg-info/requires.txt
mayavi.egg-info/top_level.txt
