Metadata-Version: 2.1
Name: mayavi
Version: 4.8.1
Summary: 3D scientific data visualization library and application
Home-page: http://docs.enthought.com/mayavi/mayavi/
Download-URL: https://www.github.com/enthought/mayavi
Author: Prabhu Ramachandran, et al.
Author-email: prabhu@aero.iitb.ac.in
Maintainer: ETS Developers
Maintainer-email: mayavi-users@lists.sf.net
License: BSD
Platform: Windows
Platform: Linux
Platform: Mac OS-X
Platform: Unix
Platform: Solaris
Classifier: Development Status :: 5 - Production/Stable
Classifier: Intended Audience :: Developers
Classifier: Intended Audience :: Science/Research
Classifier: License :: OSI Approved :: BSD License
Classifier: Operating System :: MacOS
Classifier: Operating System :: Microsoft :: Windows
Classifier: Operating System :: OS Independent
Classifier: Operating System :: POSIX
Classifier: Operating System :: Unix
Classifier: Programming Language :: C
Classifier: Programming Language :: Python
Classifier: Topic :: Scientific/Engineering
Classifier: Topic :: Software Development
Classifier: Topic :: Software Development :: Libraries
Requires-Python: >=3.7
Provides-Extra: app
License-File: LICENSE.txt
License-File: LICENSE_COLORBREWER.txt
License-File: LICENSE_YORICK.txt
